droiddepot/__init__.py
droiddepot/audio.py
droiddepot/beacon.py
droiddepot/connection.py
droiddepot/hardware.py
droiddepot/motor.py
droiddepot/notify.py
droiddepot/protocol.py
droiddepot/script.py
droiddepot/utils.py
droiddepot/voice.py
pyDroidDepot-1.1.0.dist-info/LICENSE
pyDroidDepot-1.1.0.dist-info/METADATA
pyDroidDepot-1.1.0.dist-info/WHEEL
pyDroidDepot-1.1.0.dist-info/top_level.txt
pyDroidDepot-1.1.0.dist-info/RECORD
