Metadata-Version: 2.1
Name: pyDroidDepot
Version: 1.1.0
Summary: Module for controlling droids built and purchased at the Droid Depot in Disney's Galaxys Edge
Home-page: https://github.com/thetestgame/pyDroidDepot
Author: Jordan Maxwell
Maintainer: Jordan Maxwell
License: MIT
Classifier: Programming Language :: Python :: 3
License-File: LICENSE
